[
	{
		"meal": "Margherita",
		"price": "20",
		"description": "tomato, oil, basil and mozzarella"
	},
	{
		"meal": "Marinara",
		"price": "22",
		"description": "tomato, garlic, oregano and oil"
	},
	{
		"meal": "Prosciutto e funghi",
		"price": "28",
		"description": "ham, mushroom and mozzarella"
	},
	{
		"meal": "Capricciosa",
		"price": "24",
		"description": "cooked ham, mushrooms, artichokes, tomato and mozzarella"
	},
	{
		"meal": "Quattro Formaggi",
		"price": "28",
		"description": "tomato, provolone, parmigiano reggiano,  gorgonzola, and mozzarella"
	},
	{
		"meal": "Diavola",
		"price": "24",
		"description": "tomato, spicy salami, basil and mozzarella"
	},
	{
		"meal": "Quattro Stagioni",
		"price": "26",
		"description": "cooked ham, mushrooms, artichokes, black olives, tomato and mozzarella"
	},
	{
		"meal": "Vegetariana",
		"price": "24",
		"description": "tomato, peppers, aubergines and courgette, and mozzarella"
	},
	{
		"meal": "New pizza",
		"price": "32",
		"description": "Some ingredients"
	}
]